proc_monitoring/__init__.py
proc_monitoring/exceptions/__init__.py
proc_monitoring/exceptions/monitoring_errors.py
proc_monitoring/models/__init__.py
proc_monitoring/models/message_grafana.py
proc_monitoring/nodes/__init__.py
proc_monitoring/nodes/node.py
proc_monitoring/nodes/node_dummy.py
proc_monitoring/nodes/node_eternal.py
proc_monitoring/nodes/node_gatherer.py
proc_monitoring/nodes/node_receiver.py
proc_monitoring/nodes/node_sender.py
proc_monitoring/scripts/__init__.py
proc_monitoring/scripts/executor.py
proc_monitoring/services/__init__.py
proc_monitoring/services/kafka_consumer.py
proc_monitoring/services/kafka_producer.py
proc_monitoring-1.0.1.post3.dist-info/LICENSE.md
proc_monitoring-1.0.1.post3.dist-info/METADATA
proc_monitoring-1.0.1.post3.dist-info/WHEEL
proc_monitoring-1.0.1.post3.dist-info/entry_points.txt
proc_monitoring-1.0.1.post3.dist-info/top_level.txt
proc_monitoring-1.0.1.post3.dist-info/RECORD
