Metadata-Version: 2.1
Name: proc-monitoring
Version: 1.0.1.post3
Summary: Implements methods and models for remote monitoring with Kafka and Grafana.
Home-page: UNKNOWN
Author: The_Crazy_Sys_Admin
License: UNKNOWN
Platform: UNKNOWN
Requires-Python: >=3.6.8, <4
Requires-Dist: PyYaml
Requires-Dist: requests
Requires-Dist: paramiko
Requires-Dist: kafka-python
Requires-Dist: core-commons (<2,>=1.0.2)
Provides-Extra: windows_socket_inet
Requires-Dist: win-inet-pton ; extra == 'windows_socket_inet'
